ovos_PHAL_plugin_brightness_control_rpi/__init__.py
ovos_PHAL_plugin_brightness_control_rpi/version.py
ovos_PHAL_plugin_brightness_control_rpi-1.0.0.dist-info/LICENSE
ovos_PHAL_plugin_brightness_control_rpi-1.0.0.dist-info/METADATA
ovos_PHAL_plugin_brightness_control_rpi-1.0.0.dist-info/WHEEL
ovos_PHAL_plugin_brightness_control_rpi-1.0.0.dist-info/entry_points.txt
ovos_PHAL_plugin_brightness_control_rpi-1.0.0.dist-info/top_level.txt
ovos_PHAL_plugin_brightness_control_rpi-1.0.0.dist-info/zip-safe
ovos_PHAL_plugin_brightness_control_rpi-1.0.0.dist-info/RECORD
